Metadata-Version: 2.1
Name: odoo12-addon-spec_driven_model
Version: 12.0.5.0.1
Summary: Tools for specifications driven mixins (from xsd for instance)
Home-page: https://github.com/OCA/l10n-brazil
Author: Akretion,Odoo Community Association (OCA)
Author-email: support@odoo-community.org
License: LGPL-3
Classifier: Programming Language :: Python
Classifier: Framework :: Odoo
Classifier: Framework :: Odoo :: 12.0
Classifier: License :: OSI Approved :: GNU Lesser General Public License v3 (LGPLv3)
Classifier: Development Status :: 4 - Beta
Requires-Python: >=3.5
Requires-Dist: odoo <12.1dev,>=12.0a
